spongeWebPy/__init__.py
spongeWebPy/all_ceRNAInteraction.py
spongeWebPy/config.py
spongeWebPy/dataset.py
spongeWebPy/expressionValues.py
spongeWebPy/find_miRNA.py
spongeWebPy/geneOntology.py
spongeWebPy/get_GeneCount.py
spongeWebPy/hallmarks.py
spongeWebPy/occurences.py
spongeWebPy/overview.py
spongeWebPy/specific_ceRNA.py
spongeWebPy/specific_ceRNAInteraction.py
spongeWebPy/specific_miRNAInteraction.py
spongeWebPy/survivalAnalysis.py
spongeWebPy/wikipathway.py
spongeWebPy-1.1.5.dist-info/METADATA
spongeWebPy-1.1.5.dist-info/WHEEL
spongeWebPy-1.1.5.dist-info/top_level.txt
spongeWebPy-1.1.5.dist-info/RECORD
