Metadata-Version: 2.1
Name: spongeWebPy
Version: 1.1.5
Summary: Provides user-friendly usage of the SPONGE API.
Home-page: https://github.com/biomedbigdata/spongeWebPy
Author: The List Lab - Big Data in BioMedicine
Author-email: markus.list@wzw.tum.de
License: UNKNOWN
Keywords: SPONGE API ceRNAInteractions networkAnalysis
Platform: UNKNOWN
Classifier: Development Status :: 3 - Alpha
Classifier: License :: OSI Approved :: MIT License
Classifier: Programming Language :: Python :: 3.7
Requires-Python: >=3.5, <4
Requires-Dist: certifi (>=2019.11.28)
Requires-Dist: chardet (>=3.0.4)
Requires-Dist: idna (>=2.9)
Requires-Dist: numpy (>=1.18.1)
Requires-Dist: pandas (>=1.0.1)
Requires-Dist: python-dateutil (>=2.8.1)
Requires-Dist: pytz (>=2019.3)
Requires-Dist: requests (>=2.23.0)
Requires-Dist: six (>=1.14.0)
Requires-Dist: urllib3 (>=1.25.8)
